molyso/__init__.py
molyso/__main__.py
molyso/debugging/__init__.py
molyso/debugging/callserialization.py
molyso/debugging/debugplot.py
molyso/generic/__init__.py
molyso/generic/etc.py
molyso/generic/fft.py
molyso/generic/otsu.py
molyso/generic/registration.py
molyso/generic/rotation.py
molyso/generic/signal.py
molyso/generic/smoothing.py
molyso/generic/tunable.py
molyso/mm/__init__.py
molyso/mm/cell_detection.py
molyso/mm/channel_detection.py
molyso/mm/fluorescence.py
molyso/mm/highlevel.py
molyso/mm/highlevel_interactive_advanced_ground_truth.py
molyso/mm/highlevel_interactive_ground_truth.py
molyso/mm/highlevel_interactive_viewer.py
molyso/mm/image.py
molyso/mm/tracking.py
molyso/mm/tracking_infrastructure.py
molyso/mm/tracking_output.py
molyso/test/__init__.py
molyso/test/__main__.py
molyso/test/example-frame.tif
molyso/util/__init__.py
molyso/util/molyso2vizardous/__init__.py
molyso/util/molyso2vizardous/__main__.py
molyso/util/viewkymograph/__init__.py
molyso/util/viewkymograph/__main__.py
molyso-1.0.6.dist-info/LICENSE.rst
molyso-1.0.6.dist-info/METADATA
molyso-1.0.6.dist-info/WHEEL
molyso-1.0.6.dist-info/top_level.txt
molyso-1.0.6.dist-info/RECORD
