Metadata-Version: 2.1
Name: molyso
Version: 1.0.6
Summary: MOther machine anaLYsis SOftware
Home-page: https://github.com/modsim/molyso
Author: Christian C. Sachs
Author-email: c.sachs@fz-juelich.de
License: BSD
Platform: UNKNOWN
Classifier: Development Status :: 4 - Beta
Classifier: Environment :: Console
Classifier: Intended Audience :: Science/Research
Classifier: License :: OSI Approved :: BSD License
Classifier: Operating System :: POSIX
Classifier: Operating System :: POSIX :: Linux
Classifier: Operating System :: MacOS :: MacOS X
Classifier: Operating System :: Microsoft :: Windows
Classifier: Programming Language :: Python :: 3
Classifier: Topic :: Scientific/Engineering :: Bio-Informatics
Classifier: Topic :: Scientific/Engineering :: Image Recognition
Requires-Dist: numpy
Requires-Dist: scipy
Requires-Dist: matplotlib
Requires-Dist: pilyso-io
Requires-Dist: tqdm
Requires-Dist: jsonpickle
